kdna/__init__.py
kdna/main.py
kdna-0.1.0.dist-info/METADATA
kdna-0.1.0.dist-info/WHEEL
kdna-0.1.0.dist-info/RECORD
