Metadata-Version: 2.1
Name: kdna
Version: 0.1.0
Summary: Project providing a secure way to backup and restore files on a remote server.
Home-page: https://github.com/somoslosdorados/KDNA
License: MIT
Author: D3 2023-2026
Author-email: polytech-do3@etu.umontpellier.fr
Requires-Python: >=3.10,<4.0
Classifier: License :: OSI Approved :: MIT License
Classifier: Programming Language :: Python :: 3
Classifier: Programming Language :: Python :: 3.10
Classifier: Programming Language :: Python :: 3.11
Classifier: Programming Language :: Python :: 3.12
Requires-Dist: click (>=8.1.7,<9.0.0)
Requires-Dist: fabric (>=3.2.2,<4.0.0)
Requires-Dist: pycryptodome (>=3.19.0,<4.0.0)
Project-URL: Repository, https://github.com/somoslosdorados/KDNA
